dacite/__init__.py
dacite/cache.py
dacite/config.py
dacite/core.py
dacite/data.py
dacite/dataclasses.py
dacite/exceptions.py
dacite/frozen_dict.py
dacite/py.typed
dacite/types.py
dacite-1.8.0.dist-info/LICENSE
dacite-1.8.0.dist-info/METADATA
dacite-1.8.0.dist-info/WHEEL
dacite-1.8.0.dist-info/top_level.txt
dacite-1.8.0.dist-info/RECORD
