Metadata-Version: 2.1
Name: dacite
Version: 1.8.0
Summary: Simple creation of data classes from dictionaries.
Home-page: https://github.com/konradhalas/dacite
Author: Konrad Hałas
Author-email: halas.konrad@gmail.com
License: MIT
Keywords: dataclasses
Classifier: Development Status :: 5 - Production/Stable
Classifier: Intended Audience :: Developers
Classifier: License :: OSI Approved :: MIT License
Classifier: Operating System :: OS Independent
Classifier: Programming Language :: Python
Classifier: Programming Language :: Python :: 3.6
Classifier: Programming Language :: Python :: 3.7
Classifier: Programming Language :: Python :: 3.8
Classifier: Programming Language :: Python :: 3.9
Classifier: Programming Language :: Python :: 3.10
Classifier: Programming Language :: Python :: 3.11
Classifier: Topic :: Software Development :: Libraries :: Python Modules
Requires-Python: >=3.6
Provides-Extra: dev
License-File: LICENSE
